<?xml version="1.0"?>
<opencv_storage>
<stage2>
  <maxWeakCount>3</maxWeakCount>
  <stageThreshold>-9.7122192382812500e-01</stageThreshold>
  <weakClassifiers>
    <_>
      <internalNodes>
        0 -1 84870 9.9943399429321289e-02</internalNodes>
      <leafValues>
        -8.8766789436340332e-01 7.9363059997558594e-01</leafValues></_>
    <_>
      <internalNodes>
        0 -1 138804 -2.7650252450257540e-03</internalNodes>
      <leafValues>
        6.5482527017593384e-01 -8.0006092786788940e-01</leafValues></_>
    <_>
      <internalNodes>
        0 -1 164212 -1.4063620008528233e-02</internalNodes>
      <leafValues>
        7.1650683879852295e-01 -7.0894795656204224e-01</leafValues></_></weakClassifiers></stage2>
</opencv_storage>
